MANIFEST.in
README
setup.py
confine_orm.egg-info/PKG-INFO
confine_orm.egg-info/SOURCES.txt
confine_orm.egg-info/dependency_links.txt
confine_orm.egg-info/requires.txt
confine_orm.egg-info/top_level.txt
orm/__init__.py
orm/api.py
orm/caches.py
orm/files.py
orm/helpers.py
orm/managers.py
orm/relations.py
orm/resources.py
orm/status.py
orm/utils.py
orm/tests/__init__.py
orm/tests/test_api.py
orm/tests/test_files.py
orm/tests/test_managers.py
orm/tests/test_resources.py
orm/tests/utils.py