Metadata-Version: 1.1
Name: confine-orm
Version: 0.2.1
Summary: high level Python library for easily interacting with CONFINE REST API using object oriented concepts
Home-page: http://wiki.confine-project.eu/soft:server
Author: Marc Aymerich
Author-email: marcay@pangea.org
License: BSD License
Platform: UNKNOWN
Classifier: Development Status :: 4 - Beta
Classifier: Intended Audience :: Developers
Classifier: License :: OSI Approved :: BSD License
Classifier: Operating System :: POSIX :: Linux
Classifier: Programming Language :: Python
Classifier: Programming Language :: Python :: 2.6
Classifier: Programming Language :: Python :: 2.7
Classifier: Topic :: Internet :: WWW/HTTP
Classifier: Topic :: Software Development :: Libraries :: Application Frameworks
Classifier: Topic :: Software Development :: Libraries :: Python Modules
